fletched/__init__.py
fletched/controls/__init__.py
fletched/controls/datatable.py
fletched/mvp/__init__.py
fletched/mvp/datasource.py
fletched/mvp/dialog.py
fletched/mvp/error.py
fletched/mvp/model.py
fletched/mvp/observable.py
fletched/mvp/presenter.py
fletched/mvp/protocols.py
fletched/mvp/renderer.py
fletched/mvp/view.py
fletched/routed_app/__init__.py
fletched/routed_app/app.py
fletched/routed_app/auth.py
fletched/routed_app/page_not_found.py
fletched/routed_app/routing.py
fletched/routed_app/state.py
fletched/routed_app/view_builder.py
fletched-0.5.1.dist-info/LICENSE
fletched-0.5.1.dist-info/METADATA
fletched-0.5.1.dist-info/WHEEL
fletched-0.5.1.dist-info/RECORD
