Metadata-Version: 2.1
Name: fletched
Version: 0.5.1
Summary: Tools to build flet apps with multiple views/routes
Home-page: https://iron3oxide.github.io/fletched/
License: Apache-2.0
Author: iron3oxide
Author-email: jason.hottelet@tuta.io
Requires-Python: >=3.10,<4.0
Classifier: License :: OSI Approved :: Apache Software License
Classifier: Programming Language :: Python :: 3
Classifier: Programming Language :: Python :: 3.10
Classifier: Programming Language :: Python :: 3.11
Requires-Dist: abstractcp (>=0.9.9,<0.10.0)
Requires-Dist: flet (>=0.4.0,<0.5.0)
Requires-Dist: polars (>=0.16.8,<0.17.0)
Requires-Dist: pydantic (>=1.10.5,<2.0.0)
Requires-Dist: repath (>=0.9.0,<0.10.0)
Requires-Dist: typing-extensions (>=4.5.0,<5.0.0)
Project-URL: Repository, https://github.com/iron3oxide/fletched
